{"86:1":"وَالسَّمَٓاءِ وَالطَّارِقِۙ","86:2":"وَمَٓا اَدْرٰيكَ مَا الطَّارِقُۙ","86:3":"اَلنَّجْمُ الثَّاقِبُۙ","86:4":"اِنْ كُلُّ نَفْسٍ لَمَّا عَلَيْهَا حَافِظٌۜ","86:5":"فَلْيَنْظُرِ الْاِنْسَانُ مِمَّ خُلِقَۜ","86:6":"خُلِقَ مِنْ مَٓاءٍ دَافِقٍۙ","86:7":"يَخْرُجُ مِنْ بَيْنِ الصُّلْبِ وَالتَّرَٓائِبِۜ","86:8":"اِنَّهُ عَلٰى رَجْعِه۪ لَقَادِرٌۜ","86:9":"يَوْمَ تُبْلَى السَّرَٓائِرُۙ","86:10":"فَمَا لَهُ مِنْ قُوَّةٍ وَلَا نَاصِرٍۜ","86:11":"وَالسَّمَٓاءِ ذَاتِ الرَّجْعِۙ","86:12":"وَالْاَرْضِ ذَاتِ الصَّدْعِۙ","86:13":"اِنَّهُ لَقَوْلٌ فَصْلٌۙ","86:14":"وَمَا هُوَ بِالْهَزْلِۜ","86:15":"اِنَّهُمْ يَك۪يدُونَ كَيْدًاۙ","86:16":"وَاَك۪يدُ كَيْدًاۚ","86:17":"فَمَهِّلِ الْكَافِر۪ينَ اَمْهِلْهُمْ رُوَيْدًا"}